mcnp_input_reader/__init__.py
mcnp_input_reader/cell.py
mcnp_input_reader/exceptions.py
mcnp_input_reader/fill_transformation.py
mcnp_input_reader/main.py
mcnp_input_reader/material.py
mcnp_input_reader/store.py
mcnp_input_reader/surface.py
mcnp_input_reader/util/lines.py
mcnp_input_reader/util/list_of_tuples.py
mcnp_input_reader-0.1.8.dist-info/LICENSE
mcnp_input_reader-0.1.8.dist-info/WHEEL
mcnp_input_reader-0.1.8.dist-info/METADATA
mcnp_input_reader-0.1.8.dist-info/RECORD
